alibabacloud_foasconsole20211028/__init__.py
alibabacloud_foasconsole20211028/client.py
alibabacloud_foasconsole20211028/models/__init__.py
alibabacloud_foasconsole20211028/models/_cluster_stage.py
alibabacloud_foasconsole20211028/models/_cluster_state.py
alibabacloud_foasconsole20211028/models/_convert_hybrid_instance_request.py
alibabacloud_foasconsole20211028/models/_convert_hybrid_instance_response.py
alibabacloud_foasconsole20211028/models/_convert_hybrid_instance_response_body.py
alibabacloud_foasconsole20211028/models/_convert_hybrid_instance_shrink_request.py
alibabacloud_foasconsole20211028/models/_convert_instance_request.py
alibabacloud_foasconsole20211028/models/_convert_instance_response.py
alibabacloud_foasconsole20211028/models/_convert_instance_response_body.py
alibabacloud_foasconsole20211028/models/_convert_instance_shrink_request.py
alibabacloud_foasconsole20211028/models/_convert_prepay_instance_request.py
alibabacloud_foasconsole20211028/models/_convert_prepay_instance_response.py
alibabacloud_foasconsole20211028/models/_convert_prepay_instance_response_body.py
alibabacloud_foasconsole20211028/models/_create_instance_request.py
alibabacloud_foasconsole20211028/models/_create_instance_response.py
alibabacloud_foasconsole20211028/models/_create_instance_response_body.py
alibabacloud_foasconsole20211028/models/_create_instance_shrink_request.py
alibabacloud_foasconsole20211028/models/_create_namespace_request.py
alibabacloud_foasconsole20211028/models/_create_namespace_response.py
alibabacloud_foasconsole20211028/models/_create_namespace_response_body.py
alibabacloud_foasconsole20211028/models/_create_namespace_shrink_request.py
alibabacloud_foasconsole20211028/models/_delete_instance_request.py
alibabacloud_foasconsole20211028/models/_delete_instance_response.py
alibabacloud_foasconsole20211028/models/_delete_instance_response_body.py
alibabacloud_foasconsole20211028/models/_delete_namespace_request.py
alibabacloud_foasconsole20211028-2.1.3.dist-info/LICENSE
alibabacloud_foasconsole20211028-2.1.3.dist-info/METADATA
alibabacloud_foasconsole20211028-2.1.3.dist-info/WHEEL
alibabacloud_foasconsole20211028-2.1.3.dist-info/top_level.txt
alibabacloud_foasconsole20211028-2.1.3.dist-info/RECORD
